LICENSE.txt
README.md
setup.cfg
setup.py
Scrape_LinkedIn_Jobs.egg-info/PKG-INFO
Scrape_LinkedIn_Jobs.egg-info/SOURCES.txt
Scrape_LinkedIn_Jobs.egg-info/dependency_links.txt
Scrape_LinkedIn_Jobs.egg-info/requires.txt
Scrape_LinkedIn_Jobs.egg-info/top_level.txt
scrapeLinkedinJob/__init__.py
scrapeLinkedinJob/scraper.py