Metadata-Version: 2.1
Name: Scrape-LinkedIn-Jobs
Version: 0.0.1
Summary: A simple spam bot for WhatsApp. It can spam a message a given number of times or spam forever. It can be stopped by pressing ctrl.
Home-page: https://github.com/sushilld/LinkedIn-Job-Scraper
Download-URL: https://github.com/sushilld/LinkedIn-Job-Scraper
Author: Sushil Dhakal
Author-email: sushilldhakal25@gmail.com
License: MIT
Classifier: Programming Language :: Python :: 3
Classifier: Programming Language :: Python :: 3.4
Classifier: Programming Language :: Python :: 3.5
Classifier: Programming Language :: Python :: 3.6
License-File: LICENSE.txt
